yaml2d/__init__.py
yaml2d/common.py
yaml2d/csv2yaml.py
yaml2d/generator_backend.py
yaml2d/read.py
yaml2d/write.py
yaml2d/yaml2csv.py
yaml2d-0.0.10.dist-info/LICENSE
yaml2d-0.0.10.dist-info/METADATA
yaml2d-0.0.10.dist-info/WHEEL
yaml2d-0.0.10.dist-info/top_level.txt
yaml2d-0.0.10.dist-info/RECORD
