Metadata-Version: 2.1
Name: yaml2d
Version: 0.0.10
Summary: parser of YAML2D, a tiny subset of YAML
Home-page: https://github.com/badranx/YAML-2D
Author: Yahya Badran
Author-email: techtweaking@gmail.com
License: MIT
Classifier: Programming Language :: Python :: 3
Classifier: License :: OSI Approved :: MIT License
Classifier: Operating System :: OS Independent
License-File: LICENSE
Requires-Dist: pandas >=1.0.0
